{"cameraMode":{"drawMode":0,"name":"Shaded","section":"Shading Mode"},"sceneLighting":true,"audioPlay":false,"sceneViewState":{"showFog":true,"showMaterialUpdate":false,"showSkybox":true,"showFlares":true,"showImageEffects":true,"showParticleSystems":true},"in2DMode":false,"pivot":{"x":-0.37979888916015627,"y":-16.191314697265626,"z":2.2517662048339845},"rotation":{"x":-0.21377573907375337,"y":-0.43821027874946597,"z":0.10812829434871674,"w":-0.8663602471351624},"size":81.56046295166016,"orthographic":false}